MANIFEST.in
README.md
pyproject.toml
requirements.txt
setup.cfg
setup.py
t_pom_envolve/__init__.py
t_pom_envolve/exceptions.py
t_pom_envolve/t_envolve.py
t_pom_envolve.egg-info/PKG-INFO
t_pom_envolve.egg-info/SOURCES.txt
t_pom_envolve.egg-info/dependency_links.txt
t_pom_envolve.egg-info/not-zip-safe
t_pom_envolve.egg-info/requires.txt
t_pom_envolve.egg-info/top_level.txt
t_pom_envolve/elements/__init__.py
t_pom_envolve/elements/datetime_element.py
t_pom_envolve/elements/select_element.py
t_pom_envolve/elements/table_row_element.py
t_pom_envolve/elements/text_element.py
t_pom_envolve/pages/__init__.py
t_pom_envolve/pages/login_page.py
t_pom_envolve/pages/patient_eligibility_page.py
tests/test_t_pom_envolve.py